MANIFEST.in
setup.cfg
setup.py
stratus_api/jobs/__init__.py
stratus_api/jobs/base.py
stratus_api/jobs/jobs.py
stratus_api/jobs/promises.py
stratus_api/jobs/schemas/promises.yaml
stratus_api/jobs/tasks/__init__.py
stratus_api/jobs/tasks/jobs.py
stratus_api_jobs.egg-info/PKG-INFO
stratus_api_jobs.egg-info/SOURCES.txt
stratus_api_jobs.egg-info/dependency_links.txt
stratus_api_jobs.egg-info/requires.txt
stratus_api_jobs.egg-info/top_level.txt